setup.cfg
setup.py
pyf/__init__.py
pyf.components.postprocess.email_sender.egg-info/PKG-INFO
pyf.components.postprocess.email_sender.egg-info/SOURCES.txt
pyf.components.postprocess.email_sender.egg-info/dependency_links.txt
pyf.components.postprocess.email_sender.egg-info/entry_points.txt
pyf.components.postprocess.email_sender.egg-info/namespace_packages.txt
pyf.components.postprocess.email_sender.egg-info/requires.txt
pyf.components.postprocess.email_sender.egg-info/top_level.txt
pyf.components.postprocess.email_sender.egg-info/zip-safe
pyf/components/__init__.py
pyf/components/postprocess/__init__.py
pyf/components/postprocess/email_sender/__init__.py
pyf/components/postprocess/email_sender/postprocess.py