Metadata-Version: 1.0
Name: pyf.components.postprocess.email-sender
Version: 0.2
Summary: Send emails of the output files in post-process
Home-page: http://pyfproject.org
Author: Jonathan Schemoul, Mathieu Bridon
Author-email: jonathan.schemoul@gmail.com, mathieu.bridon@gmail.com
License: MIT
Platform: UNKNOWN
Classifier: Development Status :: 3 - Alpha
Classifier: Operating System :: OS Independent
Classifier: Programming Language :: Python
Classifier: License :: OSI Approved :: MIT License
Classifier: Topic :: Software Development :: Libraries :: Python Modules
